sync_dl/__init__.py
sync_dl/cli.py
sync_dl/commands.py
sync_dl/config.py
sync_dl/helpers.py
sync_dl/plManagement.py
sync_dl/ytapiInterface.py
sync_dl/ytdlWrappers.py
sync_dl/config/__init__.py
sync_dl/config/parsing.py
sync_dl/config/tmpdir.py
sync_dl/config/ytdlParams.py
sync_dl/timestamps/__init__.py
sync_dl/timestamps/scraping.py
sync_dl/timestamps/timestamps.py
sync_dl-2.3.8.data/scripts/sync-dl
sync_dl-2.3.8.dist-info/LICENCE
sync_dl-2.3.8.dist-info/METADATA
sync_dl-2.3.8.dist-info/WHEEL
sync_dl-2.3.8.dist-info/entry_points.txt
sync_dl-2.3.8.dist-info/top_level.txt
sync_dl-2.3.8.dist-info/RECORD
