Metadata-Version: 2.1
Name: sync-dl
Version: 2.3.8
Summary: A tool for downloading and syncing remote playlists to your computer
Home-page: https://github.com/PrinceOfPuppers/sync-dl
Author: Joshua McPherson
Author-email: joshuamcpherson5@gmail.com
Classifier: Programming Language :: Python :: 3
Classifier: License :: OSI Approved :: MIT License
Classifier: Operating System :: OS Independent
Classifier: Environment :: Console
Classifier: Intended Audience :: End Users/Desktop
Requires-Python: >=3.6
License-File: LICENCE
Requires-Dist: yt-dlp
Requires-Dist: sync-dl-ytapi (>=1.1.2)
